mcp_windows_website_downloader/__init__.py
mcp_windows_website_downloader/__main__.py
mcp_windows_website_downloader/downloader.py
mcp_windows_website_downloader/server.py
mcp_windows_website_downloader/utils.py
mseep_mcp_windows_website_downloader-0.1.4.dist-info/licenses/LICENSE
mseep_mcp_windows_website_downloader-0.1.4.dist-info/METADATA
mseep_mcp_windows_website_downloader-0.1.4.dist-info/WHEEL
mseep_mcp_windows_website_downloader-0.1.4.dist-info/entry_points.txt
mseep_mcp_windows_website_downloader-0.1.4.dist-info/top_level.txt
mseep_mcp_windows_website_downloader-0.1.4.dist-info/RECORD
