Metadata-Version: 2.4
Name: mseep-mcp-windows-website-downloader
Version: 0.1.4
Summary: Simple MCP server for downloading documentation websites
Author-email: mseep <support@skydeck.ai>
Requires-Python: >=3.10
License-File: LICENSE
Requires-Dist: aiohttp>=3.8.0
Requires-Dist: beautifulsoup4>=4.9.0
Requires-Dist: mcp-python>=0.1.0
Requires-Dist: lxml>=4.9.0
Provides-Extra: dev
Requires-Dist: pytest>=6.0; extra == "dev"
Requires-Dist: black>=22.0; extra == "dev"
Requires-Dist: isort>=5.0; extra == "dev"
Dynamic: license-file
